rulekit/__init__.py
rulekit/__main__.py
rulekit/_experiment.py
rulekit/_helpers.py
rulekit/_logging.py
rulekit/_operator.py
rulekit/_problem_types.py
rulekit/arff.py
rulekit/classification.py
rulekit/events.py
rulekit/exceptions.py
rulekit/kaplan_meier.py
rulekit/main.py
rulekit/params.py
rulekit/regression.py
rulekit/rules.py
rulekit/stats.py
rulekit/survival.py
rulekit/jar/__init__.py
rulekit/jar/rulekit-2.1.24-all.jar
rulekit-2.1.24.2.dist-info/licenses/LICENSE
tests/__init__.py
tests/resources.py
tests/test_classifier.py
tests/test_regression.py
tests/test_rulekit.py
tests/test_serialization.py
tests/test_sklearn_metrics.py
tests/test_statistics.py
tests/test_survival.py
tests/utils.py
rulekit-2.1.24.2.dist-info/METADATA
rulekit-2.1.24.2.dist-info/WHEEL
rulekit-2.1.24.2.dist-info/top_level.txt
rulekit-2.1.24.2.dist-info/RECORD
