Metadata-Version: 2.4
Name: rulekit
Version: 2.1.24.2
Summary: Comprehensive suite for rule-based learning
Home-page: https://github.com/adaa-polsl/RuleKit
Author: Cezary Maszczyk
Author-email: cezary.maszczyk@gmail.com
Project-URL: Bug Tracker, https://github.com/adaa-polsl/RuleKit-python/issues
Project-URL: Documentation, https://adaa-polsl.github.io/RuleKit-python/
Project-URL: Source Code, https://github.com/adaa-polsl/RuleKit-python
Classifier: Development Status :: 4 - Beta
Classifier: License :: OSI Approved :: GNU Affero General Public License v3
Classifier: Programming Language :: Python :: 3
Classifier: Programming Language :: Java
Classifier: Operating System :: Microsoft :: Windows
Classifier: Operating System :: Unix
Classifier: Topic :: Scientific/Engineering
Classifier: Topic :: Scientific/Engineering :: Artificial Intelligence
Classifier: Intended Audience :: Developers
Classifier: Intended Audience :: Science/Research
Requires-Python: >=3.9
License-File: LICENSE
Requires-Dist: numpy>=1.24
Requires-Dist: pandas>=1.5
Requires-Dist: scipy>=1.11
Requires-Dist: scikit-learn>=1.1
Requires-Dist: JPype1==1.5.2
Requires-Dist: pydantic>=2.0
Requires-Dist: requests>=2.32.3
Dynamic: author
Dynamic: author-email
Dynamic: classifier
Dynamic: description
Dynamic: description-content-type
Dynamic: home-page
Dynamic: license-file
Dynamic: project-url
Dynamic: requires-dist
Dynamic: requires-python
Dynamic: summary
